georeport/__init__.py
georeport/cityendpoint.py
georeport/georeport.py
georeport-0.3.1.dist-info/LICENSE
georeport-0.3.1.dist-info/METADATA
georeport-0.3.1.dist-info/WHEEL
georeport-0.3.1.dist-info/RECORD
